lmair.py
light_manager_air-1.2.1.dist-info/LICENCE
light_manager_air-1.2.1.dist-info/METADATA
light_manager_air-1.2.1.dist-info/WHEEL
light_manager_air-1.2.1.dist-info/top_level.txt
light_manager_air-1.2.1.dist-info/RECORD
