Metadata-Version: 2.1
Name: light-manager-air
Version: 1.2.1
Summary: SDK for communication with jbmedia light manager air
Author-email: Korbinian Mifka <info@korbinian-mifka.com>
Project-URL: Homepage, https://github.com/kmifka/lmair-sdk-python.git
Keywords: jbmedia,smart home,light manager
Classifier: License :: OSI Approved :: MIT License
Classifier: Programming Language :: Python
Classifier: Programming Language :: Python :: 3
Requires-Python: >=3.9
License-File: LICENCE
Provides-Extra: dev
Requires-Dist: black ; extra == 'dev'
Requires-Dist: pytest ; extra == 'dev'
